<?xml version="1.0" encoding="UTF-8"?>

<!DOCTYPE hibernate-mapping PUBLIC 
"-//Hibernate/Hibernate Mapping DTD 3.0//EN"
"http://www.hibernate.org/dtd/hibernate-mapping-3.0.dtd">

<hibernate-mapping>
	<class name="com.dao.Movie" table="move_tab">
		<id name="id" column="ID" type="integer">
			<generator class="increment"></generator>
		</id>
		<property name="name">
			<column name="NAME"></column>
			<type name="string"></type>
		</property>
		<map name="details" cascade="all" table="m_detail">
			<key column="M_ID"></key>
			<index column="char_type" type="string"></index>
			<element column="char_anme" type="string"></element>
		</map>
	</class>
</hibernate-mapping>